.gitignore
LICENSE
README.md
demo.ipynb
demo.py
setup.py
dbow/__init__.py
dbow/dbow.py
dbow/orb_descriptor.py
images/0000_0085e9e41513078a_2018-08-19--13-26-08_11_864.png
images/0004_2ac95059f70d76eb_2018-05-12--17-46-52_56_371.png
images/0005_836d09212ac1b8fa_2018-06-15--15-57-15_23_345.png
images/0006_0c5c849415c7dba2_2018-08-12--10-26-26_5_1159.png
pydbow.egg-info/PKG-INFO
pydbow.egg-info/SOURCES.txt
pydbow.egg-info/dependency_links.txt
pydbow.egg-info/requires.txt
pydbow.egg-info/top_level.txt
test/test_dbow.py
test/test_descriptor.py