Metadata-Version: 2.1
Name: pydbow
Version: 0.1.2
Summary: Python Implementation of Bags of Binary Words
Home-page: https://github.com/goktug97/PyDBoW
Author: Göktuğ Karakaşlı
Author-email: karakasligk@gmail.com
License: MIT
Platform: UNKNOWN
Classifier: Programming Language :: Python :: 3
Classifier: License :: OSI Approved :: MIT License
Classifier: Operating System :: OS Independent
Requires-Python: >=3.6
License-File: LICENSE
